{
  "folder": null,
  "name": "Tai Chi (Supremo)",
  "type": "martialArtData",
  "img": "icons/svg/item-bag.svg",
  "system": {
    "grade": {
      "value": "supremo"
    },
    "artType": {
      "value": "normal"
    },
    "complexity": {
      "value": 1
    },
    "damageBase": {
      "value": 20
    },
    "damageMax": {
      "value": 0
    },
    "damageType": {
      "value": "impact"
    },
    "bonusAttack": {
      "value": 0
    },
    "bonusBlock": {
      "value": 0
    },
    "bonusDodge": {
      "value": 0
    },
    "bonusTurn": {
      "value": 0
    },
    "bonusDamage": {
      "value": 0
    },
    "bonusBreaking": {
      "value": 0
    },
    "bonusMasterAttack": {
      "value": 0
    },
    "bonusMasterDefense": {
      "value": 0
    },
    "bonusEndurance": {
      "value": 0
    },
    "critic": {
      "value": ""
    },
    "special": {
      "value": "Grado Supremo (incluye bonos de Base + Avanzado). Los bonos mostrados son los de ESTE grado, se suman a los anteriores.\n\n-"
    },
    "requirements": {
      "value": "NO"
    },
    "martialKnowledge": {
      "value": 60
    },
    "penaltyHA": {
      "value": 0
    },
    "penaltyHE": {
      "value": 0
    },
    "penaltyHP": {
      "value": 0
    }
  },
  "effects": [],
  "flags": {},
  "_stats": {
    "compendiumSource": null,
    "duplicateSource": null,
    "exportSource": null,
    "coreVersion": "14.359",
    "systemId": "animabf",
    "systemVersion": "2.3.0",
    "createdTime": null,
    "modifiedTime": null,
    "lastModifiedBy": null
  },
  "_id": "DxIm36Prk6OmaFAA",
  "sort": 0,
  "ownership": {
    "default": 0
  },
  "_key": "!items!DxIm36Prk6OmaFAA"
}