{
  "folder": null,
  "name": "Nephilim Sylvain",
  "type": "raceData",
  "img": "icons/svg/item-bag.svg",
  "system": {
    "raceType": {
      "value": "nephilim"
    },
    "rf": {
      "value": 5
    },
    "re": {
      "value": 20
    },
    "rv": {
      "value": 5
    },
    "rm": {
      "value": 10
    },
    "rp": {
      "value": 10
    },
    "agi": {
      "value": 0
    },
    "con": {
      "value": 0
    },
    "des": {
      "value": 0
    },
    "fue": {
      "value": 0
    },
    "int": {
      "value": 0
    },
    "per": {
      "value": 0
    },
    "pod": {
      "value": 0
    },
    "vol": {
      "value": 0
    },
    "size": {
      "value": 0
    },
    "regeneration": {
      "value": 1
    },
    "fatigue": {
      "value": 0
    },
    "description": {
      "value": "Resist. excepcionales, Des. hacia la luz, Curación rápida, Necesidades limitadas (1/2), Pres. lo oscuro y lo luminoso, Alma inmortal (-4 PXs)"
    }
  },
  "effects": [],
  "flags": {},
  "_stats": {
    "compendiumSource": null,
    "duplicateSource": null,
    "exportSource": null,
    "coreVersion": "14.359",
    "systemId": "animabf",
    "systemVersion": "2.3.0",
    "createdTime": null,
    "modifiedTime": null,
    "lastModifiedBy": null
  },
  "_id": "ayXKJYLnkHUTpFAA",
  "sort": 0,
  "ownership": {
    "default": 0
  },
  "_key": "!items!ayXKJYLnkHUTpFAA"
}